MANIFEST.in
__info__.py
setup.py
./appomatic_userena.egg-info/SOURCES.txt
./appomatic_userena.egg-info/dependency_links.txt
./appomatic_userena.egg-info/requires.txt
./appomatic_userena.egg-info/top_level.txt
appomatic_userena/__app__.py
appomatic_userena/__init__.py
appomatic_userena/__settings__.py
appomatic_userena/__urls__.py
appomatic_userena/models.py
appomatic_userena.egg-info/PKG-INFO
appomatic_userena.egg-info/SOURCES.txt
appomatic_userena.egg-info/dependency_links.txt
appomatic_userena.egg-info/requires.txt
appomatic_userena.egg-info/top_level.txt