Metadata-Version: 1.0
Name: appomatic-userena
Version: 0.0.32
Summary: Userena is a Django application that supplies your Django project with full account management.
Home-page: http://www.django-userena.org/
Author: RedHog (Egil Moeller)
Author-email: egil.moller@freecode.no
License: GPL
Keywords: appomatic django-userena
Platform: UNKNOWN
